gabber/__init__.py
gabber/engine/__init__.py
gabber/engine/engine.py
gabber/engine/pad.py
gabber/engine/publication.py
gabber/engine/subscription.py
gabber/engine/types.py
gabber/generated/__init__.py
gabber/generated/runtime.py
gabber/media/__init__.py
gabber/media/audio_frame.py
gabber/media/media_iterator.py
gabber/media/video_frame.py
gabber/media/virtual_camera.py
gabber/media/virtual_device.py
gabber/media/virtual_microphone.py
gabber_sdk-0.2.1.dist-info/METADATA
gabber_sdk-0.2.1.dist-info/WHEEL
gabber_sdk-0.2.1.dist-info/RECORD
