Metadata-Version: 2.4
Name: gabber-sdk
Version: 0.2.1
Summary: Python client SDK for interacting with the Gabber Engine
Project-URL: Homepage, https://github.com/gabber-dev/gabber
Project-URL: Repository, https://github.com/gabber-dev/gabber
Author-email: Neil Dwyer <neil@gabber.dev>
License-Expression: Apache-2.0
Requires-Python: >=3.11
Requires-Dist: aiohttp-retry
Requires-Dist: aiohttp~=3.0
Requires-Dist: livekit~=1.0
Requires-Dist: numpy~=2.3.2
Requires-Dist: pydantic~=2.11
